devpi_postgresql/__init__.py
devpi_postgresql/main.py
pytest_devpi_postgresql/__init__.py
devpi_postgresql-3.0.1.dist-info/METADATA
devpi_postgresql-3.0.1.dist-info/WHEEL
devpi_postgresql-3.0.1.dist-info/entry_points.txt
devpi_postgresql-3.0.1.dist-info/top_level.txt
devpi_postgresql-3.0.1.dist-info/RECORD
