Metadata-Version: 2.1
Name: devpi-postgresql
Version: 3.0.1
Summary: devpi-postgresql: a PostgreSQL storage backend for devpi-server
Home-page: https://devpi.net
Maintainer: Florian Schulze
Maintainer-email: mail@pyfidelity.com
License: MIT
Project-URL: Bug Tracker, https://github.com/devpi/devpi/issues
Project-URL: Changelog, https://github.com/devpi/devpi/blob/main/postgresql/CHANGELOG
Project-URL: Documentation, https://doc.devpi.net
Project-URL: Source Code, https://github.com/devpi/devpi
Platform: UNKNOWN
Classifier: Development Status :: 4 - Beta
Classifier: Environment :: Web Environment
Classifier: Intended Audience :: Developers
Classifier: Intended Audience :: System Administrators
Classifier: License :: OSI Approved :: MIT License
Classifier: Programming Language :: Python :: 3 :: Only
Classifier: Topic :: Internet :: WWW/HTTP
Classifier: Programming Language :: Python :: Implementation :: PyPy
Classifier: Topic :: Internet :: WWW/HTTP :: WSGI :: Application
Classifier: Programming Language :: Python :: 3.7
Classifier: Programming Language :: Python :: 3.8
Classifier: Programming Language :: Python :: 3.9
Classifier: Programming Language :: Python :: 3.10
Requires-Python: >=3.7
Requires-Dist: devpi-server (>=6.2.0)
Requires-Dist: pg8000 (>=1.17.0)
